{
  "project_info": {
    "project_number": "1064447694632",
    "project_id": "my-loans-64dd9",
    "storage_bucket": "my-loans-64dd9.appspot.com"
  },
  "client": [
    {
      "client_info": {
        "mobilesdk_app_id": "1:1064447694632:android:1f401c93fc5ba08217221d",
        "android_client_info": {
          "package_name": "com.gelson.myloans"
        }
      },
      "oauth_client": [
        {
          "client_id": "1064447694632-5q5omi2nh81u7a96mg5klmgjo6adbcvu.apps.googleusercontent.com",
          "client_type": 3
        }
      ],
      "api_key": [
        {
          "current_key": "AIzaSyBLx2s72Jgkquv9FGBPUXE-cqA8cGqR_lI"
        }
      ],
      "services": {
        "appinvite_service": {
          "other_platform_oauth_client": [
            {
              "client_id": "1064447694632-5q5omi2nh81u7a96mg5klmgjo6adbcvu.apps.googleusercontent.com",
              "client_type": 3
            }
          ]
        }
      }
    }
  ],
  "configuration_version": "1"
}